celery_rmq/__init__.py
celery_rmq/app.py
celery_rmq/errors.py
celery_rmq/exchange.py
celery_rmq/queue.py
celery_rmq/registry.py
celery_rmq/settings.py
celery_rmq/utils.py
sample/__init__.py
sample/django_sample/__init__.py
sample/standalone/__init__.py
sample/standalone/app.py
sample/standalone/consumers/__init__.py
sample/standalone/consumers/testconsumer.py
sample/standalone/testapp/__init__.py
sample/standalone/testapp/tasks.py
celery_rmq-0.0.2.dist-info/LICENSE
celery_rmq-0.0.2.dist-info/METADATA
celery_rmq-0.0.2.dist-info/WHEEL
celery_rmq-0.0.2.dist-info/top_level.txt
celery_rmq-0.0.2.dist-info/RECORD
