Metadata-Version: 2.1
Name: celery-rmq
Version: 0.0.2
Summary: Celery and RabbitMQ producer and consumer made easy with celery-rmq
Home-page: https://github.com/knroy/celery-rmq
Author: Komol Nath Roy
Author-email: rax.komol@gmail.com   
License: MIT
Platform: UNKNOWN
Classifier: License :: OSI Approved :: MIT License
Classifier: Programming Language :: Python
Classifier: Programming Language :: Python :: 3
Classifier: Programming Language :: Python :: 3.6
Classifier: Programming Language :: Python :: Implementation :: CPython
Classifier: Programming Language :: Python :: Implementation :: PyPy
Classifier: Operating System :: OS Independent
Requires-Python: >=3.6.0
Requires-Dist: celery (==4.4.2)
Requires-Dist: kombu (==4.6.8)
